MANIFEST.in
my_demo_617_20201114_05.egg-info/PKG-INFO
my_demo_617_20201114_05.egg-info/SOURCES.txt
my_demo_617_20201114_05.egg-info/dependency_links.txt
my_demo_617_20201114_05.egg-info/top_level.txt
package_test/__init__.py
package_test/setup.py